{
  "indexes": [
    {
      "collectionGroup": "testUsage",
      "queryScope": "COLLECTION",
      "fields": [
        {
          "fieldPath": "uid",
          "order": "ASCENDING"
        },
        {
          "fieldPath": "timestamp",
          "order": "DESCENDING"
        }
      ]
    },
    {
      "collectionGroup": "test_results",
      "queryScope": "COLLECTION",
      "fields": [
        {
          "fieldPath": "userId",
          "order": "ASCENDING"
        },
        {
          "fieldPath": "timestamp",
          "order": "DESCENDING"
        }
      ]
    },
    {
      "collectionGroup": "test_sessions",
      "queryScope": "COLLECTION",
      "fields": [
        {
          "fieldPath": "userId",
          "order": "ASCENDING"
        },
        {
          "fieldPath": "startTime",
          "order": "DESCENDING"
        }
      ]
    },
    {
      "collectionGroup": "activity_logs",
      "queryScope": "COLLECTION",
      "fields": [
        {
          "fieldPath": "userId",
          "order": "ASCENDING"
        },
        {
          "fieldPath": "timestamp",
          "order": "DESCENDING"
        }
      ]
    }
  ],
  "fieldOverrides": []
}
